ros_rosidl_parser-4.6.6.data/data/lib/python3.12/site-packages/rosidl_parser/__init__.py
ros_rosidl_parser-4.6.6.data/data/lib/python3.12/site-packages/rosidl_parser/definition.py
ros_rosidl_parser-4.6.6.data/data/lib/python3.12/site-packages/rosidl_parser/grammar.lark
ros_rosidl_parser-4.6.6.data/data/lib/python3.12/site-packages/rosidl_parser/parser.py
ros_rosidl_parser-4.6.6.data/data/lib/python3.12/site-packages/rosidl_parser/__pycache__/__init__.cpython-312.pyc
ros_rosidl_parser-4.6.6.data/data/lib/python3.12/site-packages/rosidl_parser/__pycache__/definition.cpython-312.pyc
ros_rosidl_parser-4.6.6.data/data/lib/python3.12/site-packages/rosidl_parser/__pycache__/parser.cpython-312.pyc
ros_rosidl_parser-4.6.6.data/data/lib/python3.12/site-packages/rosidl_parser-4.6.6-py3.12.egg-info/PKG-INFO
ros_rosidl_parser-4.6.6.data/data/lib/python3.12/site-packages/rosidl_parser-4.6.6-py3.12.egg-info/SOURCES.txt
ros_rosidl_parser-4.6.6.data/data/lib/python3.12/site-packages/rosidl_parser-4.6.6-py3.12.egg-info/dependency_links.txt
ros_rosidl_parser-4.6.6.data/data/lib/python3.12/site-packages/rosidl_parser-4.6.6-py3.12.egg-info/top_level.txt
ros_rosidl_parser-4.6.6.data/data/lib/rosidl_parser/idl2png
ros_rosidl_parser-4.6.6.data/data/share/ament_index/resource_index/package_run_dependencies/rosidl_parser
ros_rosidl_parser-4.6.6.data/data/share/ament_index/resource_index/packages/rosidl_parser
ros_rosidl_parser-4.6.6.data/data/share/ament_index/resource_index/parent_prefix_path/rosidl_parser
ros_rosidl_parser-4.6.6.data/data/share/rosidl_parser/local_setup.bash
ros_rosidl_parser-4.6.6.data/data/share/rosidl_parser/local_setup.dsv
ros_rosidl_parser-4.6.6.data/data/share/rosidl_parser/local_setup.sh
ros_rosidl_parser-4.6.6.data/data/share/rosidl_parser/local_setup.zsh
ros_rosidl_parser-4.6.6.data/data/share/rosidl_parser/package.dsv
ros_rosidl_parser-4.6.6.data/data/share/rosidl_parser/package.xml
ros_rosidl_parser-4.6.6.data/data/share/rosidl_parser/cmake/rosidl_parserConfig-version.cmake
ros_rosidl_parser-4.6.6.data/data/share/rosidl_parser/cmake/rosidl_parserConfig.cmake
ros_rosidl_parser-4.6.6.data/data/share/rosidl_parser/environment/ament_prefix_path.dsv
ros_rosidl_parser-4.6.6.data/data/share/rosidl_parser/environment/ament_prefix_path.sh
ros_rosidl_parser-4.6.6.data/data/share/rosidl_parser/environment/path.dsv
ros_rosidl_parser-4.6.6.data/data/share/rosidl_parser/environment/path.sh
ros_rosidl_parser-4.6.6.dist-info/METADATA
ros_rosidl_parser-4.6.6.dist-info/WHEEL
ros_rosidl_parser-4.6.6.dist-info/top_level.txt
ros_rosidl_parser-4.6.6.dist-info/RECORD
