Metadata-Version: 2.4
Name: ros-rosidl-parser
Version: 4.6.6
Summary: Wheel for the rosidl_parser (ros-rosidl-parser) ROS 2 package.
Requires-Dist: ros-rosidl-adapter~=4.6.6
Requires-Dist: lark-parser
Dynamic: description
Dynamic: description-content-type
Dynamic: requires-dist
Dynamic: summary
